petlja_sphinx_extensions/__init__.py
petlja_sphinx_extensions/extensions/__init__.py
petlja_sphinx_extensions/extensions/fill_in_the_blank/__init__.py
petlja_sphinx_extensions/extensions/fill_in_the_blank/fill_in_the_blank.py
petlja_sphinx_extensions/extensions/fill_in_the_blank/css/fill-in-the-blank.css
petlja_sphinx_extensions/extensions/fill_in_the_blank/images/fitb-background.svg
petlja_sphinx_extensions/extensions/fill_in_the_blank/js/fill-in-the-blank.js
petlja_sphinx_extensions/extensions/multiple_choice/__init__.py
petlja_sphinx_extensions/extensions/multiple_choice/multiple_choice.py
petlja_sphinx_extensions/extensions/multiple_choice/css/multiple-choice.css
petlja_sphinx_extensions/extensions/multiple_choice/images/choice-background.svg
petlja_sphinx_extensions/extensions/multiple_choice/images/qchoice-img.svg
petlja_sphinx_extensions/extensions/multiple_choice/js/multiple-choice.js
petlja_sphinx_extensions/extensions/notes/__init__.py
petlja_sphinx_extensions/extensions/notes/notes.py
petlja_sphinx_extensions/extensions/notes/css/notes.css
petlja_sphinx_extensions/extensions/notes/images/infonote-img.svg
petlja_sphinx_extensions/extensions/notes/images/learnmorenote-img.svg
petlja_sphinx_extensions/extensions/notes/images/question-mark.png
petlja_sphinx_extensions/extensions/notes/images/questionnote-img.svg
petlja_sphinx_extensions/extensions/notes/images/suggestionnote-img.svg
petlja_sphinx_extensions/extensions/notes/images/technicalnote-img.svg
petlja_sphinx_extensions/extensions/notes/js/notes.js
petlja_sphinx_extensions/extensions/py_code/__init__.py
petlja_sphinx_extensions/extensions/py_code/py_code.py
petlja_sphinx_extensions/extensions/py_code/css/py-code.css
petlja_sphinx_extensions/extensions/py_code/js/py-code.js
petlja_sphinx_extensions/extensions/py_code/workers/service-worker.js
petlja_sphinx_extensions/extensions/py_code/workers/web-worker.js
petlja_sphinx_extensions-1.0.9.dist-info/LICENSE
petlja_sphinx_extensions-1.0.9.dist-info/METADATA
petlja_sphinx_extensions-1.0.9.dist-info/WHEEL
petlja_sphinx_extensions-1.0.9.dist-info/top_level.txt
petlja_sphinx_extensions-1.0.9.dist-info/RECORD
