Metadata-Version: 2.1
Name: petlja-sphinx-extensions
Version: 1.0.9
Summary: Petlja's sphinx extensions for e-learning content
Home-page: UNKNOWN
Author: Fondacija Petlja
Author-email: team@petlja.org
License: UNKNOWN
Platform: UNKNOWN
Requires-Python: >=3.7
License-File: LICENSE
Requires-Dist: sphinx
